escapism.py
escapism-1.0.0.dist-info/DESCRIPTION.rst
escapism-1.0.0.dist-info/METADATA
escapism-1.0.0.dist-info/RECORD
escapism-1.0.0.dist-info/WHEEL
escapism-1.0.0.dist-info/metadata.json
escapism-1.0.0.dist-info/top_level.txt
